sphinx_excel-1.0.1-py3.9-nspkg.pth
sphinxcontrib/excel/__init__.py
sphinxcontrib/excel/cell.py
sphinxcontrib/excel/coordinate.py
sphinxcontrib/excel/excel.py
sphinxcontrib/excel/span.py
sphinxcontrib/excel/table.py
sphinx_excel-1.0.1.dist-info/LICENSE
sphinx_excel-1.0.1.dist-info/METADATA
sphinx_excel-1.0.1.dist-info/WHEEL
sphinx_excel-1.0.1.dist-info/namespace_packages.txt
sphinx_excel-1.0.1.dist-info/top_level.txt
sphinx_excel-1.0.1.dist-info/RECORD
